<?xml version="1.0" encoding="UTF-8"?>
<gc:CodeList xmlns:gc="http://docs.oasis-open.org/codelist/ns/genericode/1.0/"
             xmlns:xsi="http://www.w3.org/2001/XMLSchema-instance"
             xmlns:xoev-cl-4="http://xoev.de/schemata/genericode/4">
   <Annotation>
      <Description>
         <xoev-cl-4:shortName>sdg2relevanz</xoev-cl-4:shortName>
         <xoev-cl-4:codelistDescription>Angabe der SDG2-Relevanz</xoev-cl-4:codelistDescription>
         <xoev-cl-4:agencyShortName>SDG Koordination</xoev-cl-4:agencyShortName>
         <xoev-cl-4:validFrom>2021-09-06</xoev-cl-4:validFrom>
         <xoev-cl-4:versionHandbook>1.2</xoev-cl-4:versionHandbook>
         <xoev-cl-4:changes>Version vom 06.09.2021.</xoev-cl-4:changes>
      </Description>
   </Annotation>
   <Identification>
      <ShortName>sdg2relevanz</ShortName>
      <LongName>SDG2-Relevanz</LongName>
      <Version>0.6</Version>
      <CanonicalUri>urn:xoev-de:xevidencesurvey:codeliste:sdg2relevanz</CanonicalUri>
      <CanonicalVersionUri>urn:xoev-de:xevidencesurvey:codeliste:sdg2relevanz_0.6</CanonicalVersionUri>
      <Agency>
         <LongName>BMI SDG Koordination</LongName>
      </Agency>
   </Identification>
   <ColumnSet>
      <Column Id="code" Use="required">
         <ShortName>code</ShortName>
         <LongName>Code</LongName>
         <Data Type="string"/>
      </Column>
      <Column Id="description-de-DE" Use="required">
         <ShortName>description-de-DE</ShortName>
         <LongName>deutsche Übersetzung</LongName>
         <Data Type="string"/>
      </Column>
      <Key Id="codeKey">
         <Annotation>
            <AppInfo>
               <xoev-cl-4:recommendedKeyColumn/>
            </AppInfo>
         </Annotation>
         <ShortName>codeKey</ShortName>
         <ColumnRef Ref="code"/>
      </Key>
   </ColumnSet>
   <SimpleCodeList>
      <Row>
         <Value ColumnRef="code">
            <SimpleValue>0_keineAussage</SimpleValue>
         </Value>
         <Value ColumnRef="description-de-DE">
            <SimpleValue>keine Aussage möglich</SimpleValue>
         </Value>
      </Row>
      <Row>
         <Value ColumnRef="code">
            <SimpleValue>1_nachweis-ausstellung</SimpleValue>
         </Value>
         <Value ColumnRef="description-de-DE">
            <SimpleValue>Rechtsgrundlage "Ausstellung des Nachweises"</SimpleValue>
         </Value>
      </Row>
      <Row>
         <Value ColumnRef="code">
            <SimpleValue>2_leika</SimpleValue>
         </Value>
         <Value ColumnRef="description-de-DE">
            <SimpleValue>Rechtsgrundlage "LeiKa"</SimpleValue>
         </Value>
      </Row>
      <Row>
         <Value ColumnRef="code">
            <SimpleValue>3_leika-nachweis</SimpleValue>
         </Value>
         <Value ColumnRef="description-de-DE">
            <SimpleValue>Rechtsgrundlage "LeiKa fordert Nachweis"</SimpleValue>
         </Value>
      </Row>
   </SimpleCodeList>
</gc:CodeList>
